{
    "items": [
      {"name": "Item1", "description": "Description for Item1"},
      {"name": "Item2", "description": "Description for Item2"},
      {"name": "Item3", "description": "Description for Item3"},
      {"name": "Item4", "description": "Description for Item4"},
      {"name": "Item5", "description": "Description for Item5"},
      {"name": "Item6", "description": "Description for Item6"},
      {"name": "Item7", "description": "Description for Item7"},
      {"name": "Item8", "description": "Description for Item8"}
    ]
  }
  